[ {
  "@pi-id" : 2,
  "pi-name" : "id_0",
  "pi-instance-specific-info" : "0",
  "pi-features" : { },
  "pi-instance-id(deprecated)" : 1
} ] {
  "r-rc" : {
    "@rc-id" : 2,
    "rc-algo-exec-config" : {
      "@algo-exec-config-id" : 2,
      "algo-exec" : "echo 0",
      "algo-exec-dir" : "/home/lara06/Documents/earthquakemodels/tunning/./gamodel",
      "algo-pcs" : {
        "@pcs-id" : 2,
        "pcs-filename" : "/home/lara06/Documents/earthquakemodels/tunning/./gamodel/parameters.pcs",
        "pcs-text" : "n_generations integer [50, 150] [100]\nmutation real [0, 1] [0.1]\ninds integer [250, 750] [500]\ncrossover real [0, 1] [0.9]\n",
        "pcs-subspace" : { }
      },
      "algo-cutoff" : 3600.0,
      "algo-deterministic" : true,
      "algo-tae-context" : { }
    },
    "rc-cutoff" : 3600.0,
    "rc-pisp" : {
      "@pisp-id" : 2,
      "pisp-pi" : {
        "@pi-id" : 2
      },
      "pisp-seed" : -1
    },
    "rc-pc" : {
      "@pc-id" : 2,
      "pc-pcs" : {
        "@pcs-id" : 2
      },
      "pc-settings" : {
        "crossover" : "0.9",
        "inds" : "500",
        "mutation" : "0.1",
        "n_generations" : "100"
      },
      "pc-active-parameters" : [ "crossover", "inds", "mutation", "n_generations" ],
      "pc-forbidden" : false,
      "pc-default" : true
    },
    "rc-sample-idx" : 0
  },
  "r-run-result" : "SAT",
  "r-runtime" : 0.0,
  "r-run-length" : 0.0,
  "r-quality" : 800.0,
  "r-result-seed" : -1,
  "r-addl-run-data" : "",
  "r-wallclock-time" : 485.959
} {
  "r-rc" : {
    "@rc-id" : 3,
    "rc-algo-exec-config" : {
      "@algo-exec-config-id" : 2
    },
    "rc-cutoff" : 3600.0,
    "rc-pisp" : {
      "@pisp-id" : 2
    },
    "rc-pc" : {
      "@pc-id" : 3,
      "pc-pcs" : {
        "@pcs-id" : 2
      },
      "pc-settings" : {
        "crossover" : "0.24957469801053256",
        "inds" : "636",
        "mutation" : "0.24935965856322562",
        "n_generations" : "114"
      },
      "pc-active-parameters" : [ "crossover", "inds", "mutation", "n_generations" ],
      "pc-forbidden" : false,
      "pc-default" : false
    },
    "rc-sample-idx" : 0
  },
  "r-run-result" : "SAT",
  "r-runtime" : 234.844,
  "r-run-length" : 0.0,
  "r-quality" : 800.0,
  "r-result-seed" : -1,
  "r-addl-run-data" : "",
  "r-wallclock-time" : 346.92
} {
  "r-rc" : {
    "@rc-id" : 4,
    "rc-algo-exec-config" : {
      "@algo-exec-config-id" : 2
    },
    "rc-cutoff" : 3600.0,
    "rc-pisp" : {
      "@pisp-id" : 2
    },
    "rc-pc" : {
      "@pc-id" : 4,
      "pc-pcs" : {
        "@pcs-id" : 2
      },
      "pc-settings" : {
        "crossover" : "0.11633485689279055",
        "inds" : "553",
        "mutation" : "0.20128668499288194",
        "n_generations" : "50"
      },
      "pc-active-parameters" : [ "crossover", "inds", "mutation", "n_generations" ],
      "pc-forbidden" : false,
      "pc-default" : false
    },
    "rc-sample-idx" : 0
  },
  "r-run-result" : "SAT",
  "r-runtime" : 402.628,
  "r-run-length" : 0.0,
  "r-quality" : 800.0,
  "r-result-seed" : -1,
  "r-addl-run-data" : "",
  "r-wallclock-time" : 97.144
}