<?xml version='1.0' encoding='UTF-8'?>
<CSEPForecast xmlns='http://www.scec.org/xml-ns/csep/forecast/0.05'>
  <forecastData publicID='smi:org.scec/csep/forecast/1'>
    <modelName>gaModel-UnB_Tsukuba</modelName>
    <version>1.0</version>
    <author>PyQuake-https://github.com/PyQuake/earthquakemodels</author>
    <issueDate>2016-01-30T18:28:00Z</issueDate>
    <forecastStartDate>002010T00:00:00Z</forecastStartDate>
    <forecastEndDate>002011T00:00:00Z</forecastEndDate>
    <defaultCellDimension latRange='0.1' lonRange='0.1'/>
    <defaultMagBinDimension>0.1</defaultMagBinDimension>
    <lastMagBinOpen>1</lastMagBinOpen>
    <depthLayer max='100.0' min='0.0'>
      <cell lat='37.0' lon='139.8'>
        <bin m='3.0'>0.00102145045965</bin>
      </cell>
      <cell lat='37.1' lon='139.8'>
        <bin m='3.0'>0.00102145045965</bin>
      </cell>
      <cell lat='37.2' lon='139.8'>
        <bin m='3.0'>0.00102145045965</bin>
      </cell>
      <cell lat='37.3' lon='139.8'>
        <bin m='3.0'>0.00102145045965</bin>
      </cell>
      <cell lat='37.4' lon='139.8'>
        <bin m='3.0'>0.00102145045965</bin>
      </cell>
      <cell lat='37.5' lon='139.8'>
        <bin m='3.0'>0.00102145045965</bin>
      </cell>
      <cell lat='37.6' lon='139.8'>
        <bin m='3.0'>0.00102145045965</bin>
      </cell>
      <cell lat='37.7' lon='139.8'>
        <bin m='3.0'>0.00102145045965</bin>
      </cell>
      <cell lat='37.8' lon='139.8'>
        <bin m='3.0'>0.00102145045965</bin>
      </cell>
      <cell lat='37.9' lon='139.8'>
        <bin m='3.0'>0.00102145045965</bin>
      </cell>
      <cell lat='38.0' lon='139.8'>
        <bin m='3.0'>0.00102145045965</bin>
      </cell>
      <cell lat='38.1' lon='139.8'>
        <bin m='3.0'>0.00102145045965</bin>
      </cell>
      <cell lat='38.2' lon='139.8'>
        <bin m='3.0'>0.00102145045965</bin>
      </cell>
      <cell lat='38.3' lon='139.8'>
        <bin m='3.0'>0.00102145045965</bin>
      </cell>
      <cell lat='38.4' lon='139.8'>
        <bin m='3.0'>0.00102145045965</bin>
      </cell>
      <cell lat='38.5' lon='139.8'>
        <bin m='3.0'>0.00102145045965</bin>
      </cell>
      <cell lat='38.6' lon='139.8'>
        <bin m='3.0'>0.00102145045965</bin>
      </cell>
      <cell lat='38.7' lon='139.8'>
        <bin m='3.0'>0.00102145045965</bin>
      </cell>
      <cell lat='38.8' lon='139.8'>
        <bin m='3.0'>0.00102145045965</bin>
      </cell>
      <cell lat='38.9' lon='139.8'>
        <bin m='3.0'>0.00102145045965</bin>
      </cell>
      <cell lat='39.0' lon='139.8'>
        <bin m='3.0'>0.00102145045965</bin>
      </cell>
      <cell lat='39.1' lon='139.8'>
        <bin m='3.0'>0.00102145045965</bin>
      </cell>
      <cell lat='39.2' lon='139.8'>
        <bin m='3.0'>0.0122574055158</bin>
      </cell>
      <cell lat='39.3' lon='139.8'>
        <bin m='3.0'>0.00102145045965</bin>
      </cell>
      <cell lat='39.4' lon='139.8'>
        <bin m='3.0'>0.00102145045965</bin>
      </cell>
      <cell lat='39.5' lon='139.8'>
        <bin m='3.0'>0.00102145045965</bin>
      </cell>
      <cell lat='39.6' lon='139.8'>
        <bin m='3.0'>0.00102145045965</bin>
      </cell>
      <cell lat='39.7' lon='139.8'>
        <bin m='3.0'>0.00102145045965</bin>
      </cell>
      <cell lat='39.8' lon='139.8'>
        <bin m='3.0'>0.00102145045965</bin>
      </cell>
      <cell lat='39.9' lon='139.8'>
        <bin m='3.0'>0.00102145045965</bin>
      </cell>
      <cell lat='40.0' lon='139.8'>
        <bin m='3.0'>0.00102145045965</bin>
      </cell>
      <cell lat='40.1' lon='139.8'>
        <bin m='3.0'>0.00102145045965</bin>
      </cell>
      <cell lat='40.2' lon='139.8'>
        <bin m='3.0'>0.00102145045965</bin>
      </cell>
      <cell lat='40.3' lon='139.8'>
        <bin m='3.0'>0.00204290091931</bin>
      </cell>
      <cell lat='40.4' lon='139.8'>
        <bin m='3.0'>0.00102145045965</bin>
      </cell>
      <cell lat='40.5' lon='139.8'>
        <bin m='3.0'>0.00102145045965</bin>
      </cell>
      <cell lat='40.6' lon='139.8'>
        <bin m='3.0'>0.00102145045965</bin>
      </cell>
      <cell lat='40.7' lon='139.8'>
        <bin m='3.0'>0.00102145045965</bin>
      </cell>
      <cell lat='40.8' lon='139.8'>
        <bin m='3.0'>0.00102145045965</bin>
      </cell>
      <cell lat='40.9' lon='139.8'>
        <bin m='3.0'>0.00102145045965</bin>
      </cell>
      <cell lat='37.0' lon='139.9'>
        <bin m='3.0'>0.00102145045965</bin>
      </cell>
      <cell lat='37.1' lon='139.9'>
        <bin m='3.0'>0.00102145045965</bin>
      </cell>
      <cell lat='37.2' lon='139.9'>
        <bin m='3.0'>0.00102145045965</bin>
      </cell>
      <cell lat='37.3' lon='139.9'>
        <bin m='3.0'>0.00102145045965</bin>
      </cell>
      <cell lat='37.4' lon='139.9'>
        <bin m='3.0'>0.00102145045965</bin>
      </cell>
      <cell lat='37.5' lon='139.9'>
        <bin m='3.0'>0.00102145045965</bin>
      </cell>
      <cell lat='37.6' lon='139.9'>
        <bin m='3.0'>0.00102145045965</bin>
      </cell>
      <cell lat='37.7' lon='139.9'>
        <bin m='3.0'>0.00102145045965</bin>
      </cell>
      <cell lat='37.8' lon='139.9'>
        <bin m='3.0'>0.00102145045965</bin>
      </cell>
      <cell lat='37.9' lon='139.9'>
        <bin m='3.0'>0.00102145045965</bin>
      </cell>
      <cell lat='38.0' lon='139.9'>
        <bin m='3.0'>0.00102145045965</bin>
      </cell>
      <cell lat='38.1' lon='139.9'>
        <bin m='3.0'>0.00102145045965</bin>
      </cell>
      <cell lat='38.2' lon='139.9'>
        <bin m='3.0'>0.00102145045965</bin>
      </cell>
      <cell lat='38.3' lon='139.9'>
        <bin m='3.0'>0.00204290091931</bin>
      </cell>
      <cell lat='38.4' lon='139.9'>
        <bin m='3.0'>0.00102145045965</bin>
      </cell>
      <cell lat='38.5' lon='139.9'>
        <bin m='3.0'>0.00102145045965</bin>
      </cell>
      <cell lat='38.6' lon='139.9'>
        <bin m='3.0'>0.00102145045965</bin>
      </cell>
      <cell lat='38.7' lon='139.9'>
        <bin m='3.0'>0.00102145045965</bin>
      </cell>
      <cell lat='38.8' lon='139.9'>
        <bin m='3.0'>0.00102145045965</bin>
      </cell>
      <cell lat='38.9' lon='139.9'>
        <bin m='3.0'>0.00204290091931</bin>
      </cell>
      <cell lat='39.0' lon='139.9'>
        <bin m='3.0'>0.00102145045965</bin>
      </cell>
      <cell lat='39.1' lon='139.9'>
        <bin m='3.0'>0.00102145045965</bin>
      </cell>
      <cell lat='39.2' lon='139.9'>
        <bin m='3.0'>0.00102145045965</bin>
      </cell>
      <cell lat='39.3' lon='139.9'>
        <bin m='3.0'>0.00102145045965</bin>
      </cell>
      <cell lat='39.4' lon='139.9'>
        <bin m='3.0'>0.00102145045965</bin>
      </cell>
      <cell lat='39.5' lon='139.9'>
        <bin m='3.0'>0.00102145045965</bin>
      </cell>
      <cell lat='39.6' lon='139.9'>
        <bin m='3.0'>0.00102145045965</bin>
      </cell>
      <cell lat='39.7' lon='139.9'>
        <bin m='3.0'>0.00102145045965</bin>
      </cell>
      <cell lat='39.8' lon='139.9'>
        <bin m='3.0'>0.00102145045965</bin>
      </cell>
      <cell lat='39.9' lon='139.9'>
        <bin m='3.0'>0.00102145045965</bin>
      </cell>
      <cell lat='40.0' lon='139.9'>
        <bin m='3.0'>0.00102145045965</bin>
      </cell>
      <cell lat='40.1' lon='139.9'>
        <bin m='3.0'>0.00102145045965</bin>
      </cell>
      <cell lat='40.2' lon='139.9'>
        <bin m='3.0'>0.00102145045965</bin>
      </cell>
      <cell lat='40.3' lon='139.9'>
        <bin m='3.0'>0.00102145045965</bin>
      </cell>
      <cell lat='40.4' lon='139.9'>
        <bin m='3.0'>0.00102145045965</bin>
      </cell>
      <cell lat='40.5' lon='139.9'>
        <bin m='3.0'>0.00102145045965</bin>
      </cell>
      <cell lat='40.6' lon='139.9'>
        <bin m='3.0'>0.00102145045965</bin>
      </cell>
      <cell lat='40.7' lon='139.9'>
        <bin m='3.0'>0.00102145045965</bin>
      </cell>
      <cell lat='40.8' lon='139.9'>
        <bin m='3.0'>0.00102145045965</bin>
      </cell>
      <cell lat='40.9' lon='139.9'>
        <bin m='3.0'>0.00102145045965</bin>
      </cell>
      <cell lat='37.0' lon='140.0'>
        <bin m='3.0'>0.00102145045965</bin>
      </cell>
      <cell lat='37.1' lon='140.0'>
        <bin m='3.0'>0.00102145045965</bin>
      </cell>
      <cell lat='37.2' lon='140.0'>
        <bin m='3.0'>0.00102145045965</bin>
      </cell>
      <cell lat='37.3' lon='140.0'>
        <bin m='3.0'>0.00102145045965</bin>
      </cell>
      <cell lat='37.4' lon='140.0'>
        <bin m='3.0'>0.00102145045965</bin>
      </cell>
      <cell lat='37.5' lon='140.0'>
        <bin m='3.0'>0.00102145045965</bin>
      </cell>
      <cell lat='37.6' lon='140.0'>
        <bin m='3.0'>0.00102145045965</bin>
      </cell>
      <cell lat='37.7' lon='140.0'>
        <bin m='3.0'>0.00102145045965</bin>
      </cell>
      <cell lat='37.8' lon='140.0'>
        <bin m='3.0'>0.00102145045965</bin>
      </cell>
      <cell lat='37.9' lon='140.0'>
        <bin m='3.0'>0.00102145045965</bin>
      </cell>
      <cell lat='38.0' lon='140.0'>
        <bin m='3.0'>0.00102145045965</bin>
      </cell>
      <cell lat='38.1' lon='140.0'>
        <bin m='3.0'>0.00102145045965</bin>
      </cell>
      <cell lat='38.2' lon='140.0'>
        <bin m='3.0'>0.00102145045965</bin>
      </cell>
      <cell lat='38.3' lon='140.0'>
        <bin m='3.0'>0.00102145045965</bin>
      </cell>
      <cell lat='38.4' lon='140.0'>
        <bin m='3.0'>0.00102145045965</bin>
      </cell>
      <cell lat='38.5' lon='140.0'>
        <bin m='3.0'>0.00102145045965</bin>
      </cell>
      <cell lat='38.6' lon='140.0'>
        <bin m='3.0'>0.00102145045965</bin>
      </cell>
      <cell lat='38.7' lon='140.0'>
        <bin m='3.0'>0.00102145045965</bin>
      </cell>
      <cell lat='38.8' lon='140.0'>
        <bin m='3.0'>0.00102145045965</bin>
      </cell>
      <cell lat='38.9' lon='140.0'>
        <bin m='3.0'>0.00102145045965</bin>
      </cell>
      <cell lat='39.0' lon='140.0'>
        <bin m='3.0'>0.00102145045965</bin>
      </cell>
      <cell lat='39.1' lon='140.0'>
        <bin m='3.0'>0.00102145045965</bin>
      </cell>
      <cell lat='39.2' lon='140.0'>
        <bin m='3.0'>0.00102145045965</bin>
      </cell>
      <cell lat='39.3' lon='140.0'>
        <bin m='3.0'>0.00102145045965</bin>
      </cell>
      <cell lat='39.4' lon='140.0'>
        <bin m='3.0'>0.00204290091931</bin>
      </cell>
      <cell lat='39.5' lon='140.0'>
        <bin m='3.0'>0.00102145045965</bin>
      </cell>
      <cell lat='39.6' lon='140.0'>
        <bin m='3.0'>0.00102145045965</bin>
      </cell>
      <cell lat='39.7' lon='140.0'>
        <bin m='3.0'>0.00102145045965</bin>
      </cell>
      <cell lat='39.8' lon='140.0'>
        <bin m='3.0'>0.00102145045965</bin>
      </cell>
      <cell lat='39.9' lon='140.0'>
        <bin m='3.0'>0.0122574055158</bin>
      </cell>
      <cell lat='40.0' lon='140.0'>
        <bin m='3.0'>0.00102145045965</bin>
      </cell>
      <cell lat='40.1' lon='140.0'>
        <bin m='3.0'>0.00102145045965</bin>
      </cell>
      <cell lat='40.2' lon='140.0'>
        <bin m='3.0'>0.00102145045965</bin>
      </cell>
      <cell lat='40.3' lon='140.0'>
        <bin m='3.0'>0.00102145045965</bin>
      </cell>
      <cell lat='40.4' lon='140.0'>
        <bin m='3.0'>0.00102145045965</bin>
      </cell>
      <cell lat='40.5' lon='140.0'>
        <bin m='3.0'>0.00102145045965</bin>
      </cell>
      <cell lat='40.6' lon='140.0'>
        <bin m='3.0'>0.0122574055158</bin>
      </cell>
      <cell lat='40.7' lon='140.0'>
        <bin m='3.0'>0.00102145045965</bin>
      </cell>
      <cell lat='40.8' lon='140.0'>
        <bin m='3.0'>0.00102145045965</bin>
      </cell>
      <cell lat='40.9' lon='140.0'>
        <bin m='3.0'>0.00102145045965</bin>
      </cell>
      <cell lat='37.0' lon='140.1'>
        <bin m='3.0'>0.00102145045965</bin>
      </cell>
      <cell lat='37.1' lon='140.1'>
        <bin m='3.0'>0.00102145045965</bin>
      </cell>
      <cell lat='37.2' lon='140.1'>
        <bin m='3.0'>0.00204290091931</bin>
      </cell>
      <cell lat='37.3' lon='140.1'>
        <bin m='3.0'>0.00102145045965</bin>
      </cell>
      <cell lat='37.4' lon='140.1'>
        <bin m='3.0'>0.00102145045965</bin>
      </cell>
      <cell lat='37.5' lon='140.1'>
        <bin m='3.0'>0.00102145045965</bin>
      </cell>
      <cell lat='37.6' lon='140.1'>
        <bin m='3.0'>0.00102145045965</bin>
      </cell>
      <cell lat='37.7' lon='140.1'>
        <bin m='3.0'>0.00102145045965</bin>
      </cell>
      <cell lat='37.8' lon='140.1'>
        <bin m='3.0'>0.00102145045965</bin>
      </cell>
      <cell lat='37.9' lon='140.1'>
        <bin m='3.0'>0.00102145045965</bin>
      </cell>
      <cell lat='38.0' lon='140.1'>
        <bin m='3.0'>0.00102145045965</bin>
      </cell>
      <cell lat='38.1' lon='140.1'>
        <bin m='3.0'>0.00102145045965</bin>
      </cell>
      <cell lat='38.2' lon='140.1'>
        <bin m='3.0'>0.00102145045965</bin>
      </cell>
      <cell lat='38.3' lon='140.1'>
        <bin m='3.0'>0.00102145045965</bin>
      </cell>
      <cell lat='38.4' lon='140.1'>
        <bin m='3.0'>0.00102145045965</bin>
      </cell>
      <cell lat='38.5' lon='140.1'>
        <bin m='3.0'>0.00102145045965</bin>
      </cell>
      <cell lat='38.6' lon='140.1'>
        <bin m='3.0'>0.00102145045965</bin>
      </cell>
      <cell lat='38.7' lon='140.1'>
        <bin m='3.0'>0.00102145045965</bin>
      </cell>
      <cell lat='38.8' lon='140.1'>
        <bin m='3.0'>0.00102145045965</bin>
      </cell>
      <cell lat='38.9' lon='140.1'>
        <bin m='3.0'>0.00102145045965</bin>
      </cell>
      <cell lat='39.0' lon='140.1'>
        <bin m='3.0'>0.00102145045965</bin>
      </cell>
      <cell lat='39.1' lon='140.1'>
        <bin m='3.0'>0.00306435137896</bin>
      </cell>
      <cell lat='39.2' lon='140.1'>
        <bin m='3.0'>0.00102145045965</bin>
      </cell>
      <cell lat='39.3' lon='140.1'>
        <bin m='3.0'>0.00102145045965</bin>
      </cell>
      <cell lat='39.4' lon='140.1'>
        <bin m='3.0'>0.00102145045965</bin>
      </cell>
      <cell lat='39.5' lon='140.1'>
        <bin m='3.0'>0.00102145045965</bin>
      </cell>
      <cell lat='39.6' lon='140.1'>
        <bin m='3.0'>0.00102145045965</bin>
      </cell>
      <cell lat='39.7' lon='140.1'>
        <bin m='3.0'>0.00102145045965</bin>
      </cell>
      <cell lat='39.8' lon='140.1'>
        <bin m='3.0'>0.00102145045965</bin>
      </cell>
      <cell lat='39.9' lon='140.1'>
        <bin m='3.0'>0.00102145045965</bin>
      </cell>
      <cell lat='40.0' lon='140.1'>
        <bin m='3.0'>0.00102145045965</bin>
      </cell>
      <cell lat='40.1' lon='140.1'>
        <bin m='3.0'>0.00102145045965</bin>
      </cell>
      <cell lat='40.2' lon='140.1'>
        <bin m='3.0'>0.00102145045965</bin>
      </cell>
      <cell lat='40.3' lon='140.1'>
        <bin m='3.0'>0.00102145045965</bin>
      </cell>
      <cell lat='40.4' lon='140.1'>
        <bin m='3.0'>0.00102145045965</bin>
      </cell>
      <cell lat='40.5' lon='140.1'>
        <bin m='3.0'>0.00408580183861</bin>
      </cell>
      <cell lat='40.6' lon='140.1'>
        <bin m='3.0'>0.00102145045965</bin>
      </cell>
      <cell lat='40.7' lon='140.1'>
        <bin m='3.0'>0.00102145045965</bin>
      </cell>
      <cell lat='40.8' lon='140.1'>
        <bin m='3.0'>0.00102145045965</bin>
      </cell>
      <cell lat='40.9' lon='140.1'>
        <bin m='3.0'>0.00102145045965</bin>
      </cell>
      <cell lat='37.0' lon='140.2'>
        <bin m='3.0'>0.00204290091931</bin>
      </cell>
      <cell lat='37.1' lon='140.2'>
        <bin m='3.0'>0.00102145045965</bin>
      </cell>
      <cell lat='37.2' lon='140.2'>
        <bin m='3.0'>0.00102145045965</bin>
      </cell>
      <cell lat='37.3' lon='140.2'>
        <bin m='3.0'>0.00102145045965</bin>
      </cell>
      <cell lat='37.4' lon='140.2'>
        <bin m='3.0'>0.00102145045965</bin>
      </cell>
      <cell lat='37.5' lon='140.2'>
        <bin m='3.0'>0.00102145045965</bin>
      </cell>
      <cell lat='37.6' lon='140.2'>
        <bin m='3.0'>0.00102145045965</bin>
      </cell>
      <cell lat='37.7' lon='140.2'>
        <bin m='3.0'>0.00102145045965</bin>
      </cell>
      <cell lat='37.8' lon='140.2'>
        <bin m='3.0'>0.00102145045965</bin>
      </cell>
      <cell lat='37.9' lon='140.2'>
        <bin m='3.0'>0.00102145045965</bin>
      </cell>
      <cell lat='38.0' lon='140.2'>
        <bin m='3.0'>0.00102145045965</bin>
      </cell>
      <cell lat='38.1' lon='140.2'>
        <bin m='3.0'>0.00102145045965</bin>
      </cell>
      <cell lat='38.2' lon='140.2'>
        <bin m='3.0'>0.00102145045965</bin>
      </cell>
      <cell lat='38.3' lon='140.2'>
        <bin m='3.0'>0.00102145045965</bin>
      </cell>
      <cell lat='38.4' lon='140.2'>
        <bin m='3.0'>0.00102145045965</bin>
      </cell>
      <cell lat='38.5' lon='140.2'>
        <bin m='3.0'>0.00102145045965</bin>
      </cell>
      <cell lat='38.6' lon='140.2'>
        <bin m='3.0'>0.00102145045965</bin>
      </cell>
      <cell lat='38.7' lon='140.2'>
        <bin m='3.0'>0.00102145045965</bin>
      </cell>
      <cell lat='38.8' lon='140.2'>
        <bin m='3.0'>0.00102145045965</bin>
      </cell>
      <cell lat='38.9' lon='140.2'>
        <bin m='3.0'>0.00102145045965</bin>
      </cell>
      <cell lat='39.0' lon='140.2'>
        <bin m='3.0'>0.00102145045965</bin>
      </cell>
      <cell lat='39.1' lon='140.2'>
        <bin m='3.0'>0.00306435137896</bin>
      </cell>
      <cell lat='39.2' lon='140.2'>
        <bin m='3.0'>0.00102145045965</bin>
      </cell>
      <cell lat='39.3' lon='140.2'>
        <bin m='3.0'>0.00102145045965</bin>
      </cell>
      <cell lat='39.4' lon='140.2'>
        <bin m='3.0'>0.00204290091931</bin>
      </cell>
      <cell lat='39.5' lon='140.2'>
        <bin m='3.0'>0.00102145045965</bin>
      </cell>
      <cell lat='39.6' lon='140.2'>
        <bin m='3.0'>0.00102145045965</bin>
      </cell>
      <cell lat='39.7' lon='140.2'>
        <bin m='3.0'>0.00102145045965</bin>
      </cell>
      <cell lat='39.8' lon='140.2'>
        <bin m='3.0'>0.00102145045965</bin>
      </cell>
      <cell lat='39.9' lon='140.2'>
        <bin m='3.0'>0.00204290091931</bin>
      </cell>
      <cell lat='40.0' lon='140.2'>
        <bin m='3.0'>0.00102145045965</bin>
      </cell>
      <cell lat='40.1' lon='140.2'>
        <bin m='3.0'>0.00102145045965</bin>
      </cell>
      <cell lat='40.2' lon='140.2'>
        <bin m='3.0'>0.00102145045965</bin>
      </cell>
      <cell lat='40.3' lon='140.2'>
        <bin m='3.0'>0.00102145045965</bin>
      </cell>
      <cell lat='40.4' lon='140.2'>
        <bin m='3.0'>0.00102145045965</bin>
      </cell>
      <cell lat='40.5' lon='140.2'>
        <bin m='3.0'>0.00102145045965</bin>
      </cell>
      <cell lat='40.6' lon='140.2'>
        <bin m='3.0'>0.00102145045965</bin>
      </cell>
      <cell lat='40.7' lon='140.2'>
        <bin m='3.0'>0.00102145045965</bin>
      </cell>
      <cell lat='40.8' lon='140.2'>
        <bin m='3.0'>0.00102145045965</bin>
      </cell>
      <cell lat='40.9' lon='140.2'>
        <bin m='3.0'>0.00102145045965</bin>
      </cell>
      <cell lat='37.0' lon='140.3'>
        <bin m='3.0'>0.00102145045965</bin>
      </cell>
      <cell lat='37.1' lon='140.3'>
        <bin m='3.0'>0.00102145045965</bin>
      </cell>
      <cell lat='37.2' lon='140.3'>
        <bin m='3.0'>0.00102145045965</bin>
      </cell>
      <cell lat='37.3' lon='140.3'>
        <bin m='3.0'>0.00204290091931</bin>
      </cell>
      <cell lat='37.4' lon='140.3'>
        <bin m='3.0'>0.00102145045965</bin>
      </cell>
      <cell lat='37.5' lon='140.3'>
        <bin m='3.0'>0.00102145045965</bin>
      </cell>
      <cell lat='37.6' lon='140.3'>
        <bin m='3.0'>0.00102145045965</bin>
      </cell>
      <cell lat='37.7' lon='140.3'>
        <bin m='3.0'>0.00102145045965</bin>
      </cell>
      <cell lat='37.8' lon='140.3'>
        <bin m='3.0'>0.00102145045965</bin>
      </cell>
      <cell lat='37.9' lon='140.3'>
        <bin m='3.0'>0.00102145045965</bin>
      </cell>
      <cell lat='38.0' lon='140.3'>
        <bin m='3.0'>0.00102145045965</bin>
      </cell>
      <cell lat='38.1' lon='140.3'>
        <bin m='3.0'>0.00102145045965</bin>
      </cell>
      <cell lat='38.2' lon='140.3'>
        <bin m='3.0'>0.00102145045965</bin>
      </cell>
      <cell lat='38.3' lon='140.3'>
        <bin m='3.0'>0.00102145045965</bin>
      </cell>
      <cell lat='38.4' lon='140.3'>
        <bin m='3.0'>0.00204290091931</bin>
      </cell>
      <cell lat='38.5' lon='140.3'>
        <bin m='3.0'>0.00102145045965</bin>
      </cell>
      <cell lat='38.6' lon='140.3'>
        <bin m='3.0'>0.00102145045965</bin>
      </cell>
      <cell lat='38.7' lon='140.3'>
        <bin m='3.0'>0.00102145045965</bin>
      </cell>
      <cell lat='38.8' lon='140.3'>
        <bin m='3.0'>0.00102145045965</bin>
      </cell>
      <cell lat='38.9' lon='140.3'>
        <bin m='3.0'>0.00102145045965</bin>
      </cell>
      <cell lat='39.0' lon='140.3'>
        <bin m='3.0'>0.00102145045965</bin>
      </cell>
      <cell lat='39.1' lon='140.3'>
        <bin m='3.0'>0.00102145045965</bin>
      </cell>
      <cell lat='39.2' lon='140.3'>
        <bin m='3.0'>0.00102145045965</bin>
      </cell>
      <cell lat='39.3' lon='140.3'>
        <bin m='3.0'>0.00102145045965</bin>
      </cell>
      <cell lat='39.4' lon='140.3'>
        <bin m='3.0'>0.00102145045965</bin>
      </cell>
      <cell lat='39.5' lon='140.3'>
        <bin m='3.0'>0.00102145045965</bin>
      </cell>
      <cell lat='39.6' lon='140.3'>
        <bin m='3.0'>0.00102145045965</bin>
      </cell>
      <cell lat='39.7' lon='140.3'>
        <bin m='3.0'>0.00102145045965</bin>
      </cell>
      <cell lat='39.8' lon='140.3'>
        <bin m='3.0'>0.00102145045965</bin>
      </cell>
      <cell lat='39.9' lon='140.3'>
        <bin m='3.0'>0.00102145045965</bin>
      </cell>
      <cell lat='40.0' lon='140.3'>
        <bin m='3.0'>0.00102145045965</bin>
      </cell>
      <cell lat='40.1' lon='140.3'>
        <bin m='3.0'>0.00102145045965</bin>
      </cell>
      <cell lat='40.2' lon='140.3'>
        <bin m='3.0'>0.00102145045965</bin>
      </cell>
      <cell lat='40.3' lon='140.3'>
        <bin m='3.0'>0.00102145045965</bin>
      </cell>
      <cell lat='40.4' lon='140.3'>
        <bin m='3.0'>0.00102145045965</bin>
      </cell>
      <cell lat='40.5' lon='140.3'>
        <bin m='3.0'>0.00102145045965</bin>
      </cell>
      <cell lat='40.6' lon='140.3'>
        <bin m='3.0'>0.00102145045965</bin>
      </cell>
      <cell lat='40.7' lon='140.3'>
        <bin m='3.0'>0.00102145045965</bin>
      </cell>
      <cell lat='40.8' lon='140.3'>
        <bin m='3.0'>0.00102145045965</bin>
      </cell>
      <cell lat='40.9' lon='140.3'>
        <bin m='3.0'>0.00102145045965</bin>
      </cell>
      <cell lat='37.0' lon='140.4'>
        <bin m='3.0'>0.00102145045965</bin>
      </cell>
      <cell lat='37.1' lon='140.4'>
        <bin m='3.0'>0.00102145045965</bin>
      </cell>
      <cell lat='37.2' lon='140.4'>
        <bin m='3.0'>0.00102145045965</bin>
      </cell>
      <cell lat='37.3' lon='140.4'>
        <bin m='3.0'>0.00102145045965</bin>
      </cell>
      <cell lat='37.4' lon='140.4'>
        <bin m='3.0'>0.00102145045965</bin>
      </cell>
      <cell lat='37.5' lon='140.4'>
        <bin m='3.0'>0.00102145045965</bin>
      </cell>
      <cell lat='37.6' lon='140.4'>
        <bin m='3.0'>0.00408580183861</bin>
      </cell>
      <cell lat='37.7' lon='140.4'>
        <bin m='3.0'>0.00102145045965</bin>
      </cell>
      <cell lat='37.8' lon='140.4'>
        <bin m='3.0'>0.00102145045965</bin>
      </cell>
      <cell lat='37.9' lon='140.4'>
        <bin m='3.0'>0.00102145045965</bin>
      </cell>
      <cell lat='38.0' lon='140.4'>
        <bin m='3.0'>0.00102145045965</bin>
      </cell>
      <cell lat='38.1' lon='140.4'>
        <bin m='3.0'>0.00102145045965</bin>
      </cell>
      <cell lat='38.2' lon='140.4'>
        <bin m='3.0'>0.00102145045965</bin>
      </cell>
      <cell lat='38.3' lon='140.4'>
        <bin m='3.0'>0.00204290091931</bin>
      </cell>
      <cell lat='38.4' lon='140.4'>
        <bin m='3.0'>0.00715015321757</bin>
      </cell>
      <cell lat='38.5' lon='140.4'>
        <bin m='3.0'>0.00204290091931</bin>
      </cell>
      <cell lat='38.6' lon='140.4'>
        <bin m='3.0'>0.00102145045965</bin>
      </cell>
      <cell lat='38.7' lon='140.4'>
        <bin m='3.0'>0.00102145045965</bin>
      </cell>
      <cell lat='38.8' lon='140.4'>
        <bin m='3.0'>0.00102145045965</bin>
      </cell>
      <cell lat='38.9' lon='140.4'>
        <bin m='3.0'>0.00102145045965</bin>
      </cell>
      <cell lat='39.0' lon='140.4'>
        <bin m='3.0'>0.00510725229826</bin>
      </cell>
      <cell lat='39.1' lon='140.4'>
        <bin m='3.0'>0.00408580183861</bin>
      </cell>
      <cell lat='39.2' lon='140.4'>
        <bin m='3.0'>0.00102145045965</bin>
      </cell>
      <cell lat='39.3' lon='140.4'>
        <bin m='3.0'>0.00102145045965</bin>
      </cell>
      <cell lat='39.4' lon='140.4'>
        <bin m='3.0'>0.00102145045965</bin>
      </cell>
      <cell lat='39.5' lon='140.4'>
        <bin m='3.0'>0.00102145045965</bin>
      </cell>
      <cell lat='39.6' lon='140.4'>
        <bin m='3.0'>0.00102145045965</bin>
      </cell>
      <cell lat='39.7' lon='140.4'>
        <bin m='3.0'>0.00102145045965</bin>
      </cell>
      <cell lat='39.8' lon='140.4'>
        <bin m='3.0'>0.00102145045965</bin>
      </cell>
      <cell lat='39.9' lon='140.4'>
        <bin m='3.0'>0.00102145045965</bin>
      </cell>
      <cell lat='40.0' lon='140.4'>
        <bin m='3.0'>0.00102145045965</bin>
      </cell>
      <cell lat='40.1' lon='140.4'>
        <bin m='3.0'>0.00102145045965</bin>
      </cell>
      <cell lat='40.2' lon='140.4'>
        <bin m='3.0'>0.00102145045965</bin>
      </cell>
      <cell lat='40.3' lon='140.4'>
        <bin m='3.0'>0.00306435137896</bin>
      </cell>
      <cell lat='40.4' lon='140.4'>
        <bin m='3.0'>0.00102145045965</bin>
      </cell>
      <cell lat='40.5' lon='140.4'>
        <bin m='3.0'>0.00102145045965</bin>
      </cell>
      <cell lat='40.6' lon='140.4'>
        <bin m='3.0'>0.00102145045965</bin>
      </cell>
      <cell lat='40.7' lon='140.4'>
        <bin m='3.0'>0.00102145045965</bin>
      </cell>
      <cell lat='40.8' lon='140.4'>
        <bin m='3.0'>0.00102145045965</bin>
      </cell>
      <cell lat='40.9' lon='140.4'>
        <bin m='3.0'>0.00102145045965</bin>
      </cell>
      <cell lat='37.0' lon='140.5'>
        <bin m='3.0'>0.00102145045965</bin>
      </cell>
      <cell lat='37.1' lon='140.5'>
        <bin m='3.0'>0.00102145045965</bin>
      </cell>
      <cell lat='37.2' lon='140.5'>
        <bin m='3.0'>0.00102145045965</bin>
      </cell>
      <cell lat='37.3' lon='140.5'>
        <bin m='3.0'>0.00102145045965</bin>
      </cell>
      <cell lat='37.4' lon='140.5'>
        <bin m='3.0'>0.00204290091931</bin>
      </cell>
      <cell lat='37.5' lon='140.5'>
        <bin m='3.0'>0.00102145045965</bin>
      </cell>
      <cell lat='37.6' lon='140.5'>
        <bin m='3.0'>0.00102145045965</bin>
      </cell>
      <cell lat='37.7' lon='140.5'>
        <bin m='3.0'>0.00102145045965</bin>
      </cell>
      <cell lat='37.8' lon='140.5'>
        <bin m='3.0'>0.00102145045965</bin>
      </cell>
      <cell lat='37.9' lon='140.5'>
        <bin m='3.0'>0.00204290091931</bin>
      </cell>
      <cell lat='38.0' lon='140.5'>
        <bin m='3.0'>0.00102145045965</bin>
      </cell>
      <cell lat='38.1' lon='140.5'>
        <bin m='3.0'>0.00306435137896</bin>
      </cell>
      <cell lat='38.2' lon='140.5'>
        <bin m='3.0'>0.00715015321757</bin>
      </cell>
      <cell lat='38.3' lon='140.5'>
        <bin m='3.0'>0.00102145045965</bin>
      </cell>
      <cell lat='38.4' lon='140.5'>
        <bin m='3.0'>0.00204290091931</bin>
      </cell>
      <cell lat='38.5' lon='140.5'>
        <bin m='3.0'>0.00102145045965</bin>
      </cell>
      <cell lat='38.6' lon='140.5'>
        <bin m='3.0'>0.00102145045965</bin>
      </cell>
      <cell lat='38.7' lon='140.5'>
        <bin m='3.0'>0.00102145045965</bin>
      </cell>
      <cell lat='38.8' lon='140.5'>
        <bin m='3.0'>0.00102145045965</bin>
      </cell>
      <cell lat='38.9' lon='140.5'>
        <bin m='3.0'>0.00102145045965</bin>
      </cell>
      <cell lat='39.0' lon='140.5'>
        <bin m='3.0'>0.00102145045965</bin>
      </cell>
      <cell lat='39.1' lon='140.5'>
        <bin m='3.0'>0.00204290091931</bin>
      </cell>
      <cell lat='39.2' lon='140.5'>
        <bin m='3.0'>0.00102145045965</bin>
      </cell>
      <cell lat='39.3' lon='140.5'>
        <bin m='3.0'>0.00204290091931</bin>
      </cell>
      <cell lat='39.4' lon='140.5'>
        <bin m='3.0'>0.00102145045965</bin>
      </cell>
      <cell lat='39.5' lon='140.5'>
        <bin m='3.0'>0.00204290091931</bin>
      </cell>
      <cell lat='39.6' lon='140.5'>
        <bin m='3.0'>0.00102145045965</bin>
      </cell>
      <cell lat='39.7' lon='140.5'>
        <bin m='3.0'>0.00102145045965</bin>
      </cell>
      <cell lat='39.8' lon='140.5'>
        <bin m='3.0'>0.00102145045965</bin>
      </cell>
      <cell lat='39.9' lon='140.5'>
        <bin m='3.0'>0.00102145045965</bin>
      </cell>
      <cell lat='40.0' lon='140.5'>
        <bin m='3.0'>0.00102145045965</bin>
      </cell>
      <cell lat='40.1' lon='140.5'>
        <bin m='3.0'>0.00102145045965</bin>
      </cell>
      <cell lat='40.2' lon='140.5'>
        <bin m='3.0'>0.00102145045965</bin>
      </cell>
      <cell lat='40.3' lon='140.5'>
        <bin m='3.0'>0.00102145045965</bin>
      </cell>
      <cell lat='40.4' lon='140.5'>
        <bin m='3.0'>0.00102145045965</bin>
      </cell>
      <cell lat='40.5' lon='140.5'>
        <bin m='3.0'>0.00102145045965</bin>
      </cell>
      <cell lat='40.6' lon='140.5'>
        <bin m='3.0'>0.00102145045965</bin>
      </cell>
      <cell lat='40.7' lon='140.5'>
        <bin m='3.0'>0.00102145045965</bin>
      </cell>
      <cell lat='40.8' lon='140.5'>
        <bin m='3.0'>0.00102145045965</bin>
      </cell>
      <cell lat='40.9' lon='140.5'>
        <bin m='3.0'>0.00102145045965</bin>
      </cell>
      <cell lat='37.0' lon='140.6'>
        <bin m='3.0'>0.00102145045965</bin>
      </cell>
      <cell lat='37.1' lon='140.6'>
        <bin m='3.0'>0.00204290091931</bin>
      </cell>
      <cell lat='37.2' lon='140.6'>
        <bin m='3.0'>0.00102145045965</bin>
      </cell>
      <cell lat='37.3' lon='140.6'>
        <bin m='3.0'>0.00102145045965</bin>
      </cell>
      <cell lat='37.4' lon='140.6'>
        <bin m='3.0'>0.00102145045965</bin>
      </cell>
      <cell lat='37.5' lon='140.6'>
        <bin m='3.0'>0.00102145045965</bin>
      </cell>
      <cell lat='37.6' lon='140.6'>
        <bin m='3.0'>0.00102145045965</bin>
      </cell>
      <cell lat='37.7' lon='140.6'>
        <bin m='3.0'>0.00102145045965</bin>
      </cell>
      <cell lat='37.8' lon='140.6'>
        <bin m='3.0'>0.00817160367722</bin>
      </cell>
      <cell lat='37.9' lon='140.6'>
        <bin m='3.0'>0.00102145045965</bin>
      </cell>
      <cell lat='38.0' lon='140.6'>
        <bin m='3.0'>0.00102145045965</bin>
      </cell>
      <cell lat='38.1' lon='140.6'>
        <bin m='3.0'>0.00102145045965</bin>
      </cell>
      <cell lat='38.2' lon='140.6'>
        <bin m='3.0'>0.00102145045965</bin>
      </cell>
      <cell lat='38.3' lon='140.6'>
        <bin m='3.0'>0.00102145045965</bin>
      </cell>
      <cell lat='38.4' lon='140.6'>
        <bin m='3.0'>0.00102145045965</bin>
      </cell>
      <cell lat='38.5' lon='140.6'>
        <bin m='3.0'>0.00102145045965</bin>
      </cell>
      <cell lat='38.6' lon='140.6'>
        <bin m='3.0'>0.00102145045965</bin>
      </cell>
      <cell lat='38.7' lon='140.6'>
        <bin m='3.0'>0.00102145045965</bin>
      </cell>
      <cell lat='38.8' lon='140.6'>
        <bin m='3.0'>0.00102145045965</bin>
      </cell>
      <cell lat='38.9' lon='140.6'>
        <bin m='3.0'>0.00204290091931</bin>
      </cell>
      <cell lat='39.0' lon='140.6'>
        <bin m='3.0'>0.00102145045965</bin>
      </cell>
      <cell lat='39.1' lon='140.6'>
        <bin m='3.0'>0.00102145045965</bin>
      </cell>
      <cell lat='39.2' lon='140.6'>
        <bin m='3.0'>0.00204290091931</bin>
      </cell>
      <cell lat='39.3' lon='140.6'>
        <bin m='3.0'>0.00102145045965</bin>
      </cell>
      <cell lat='39.4' lon='140.6'>
        <bin m='3.0'>0.00102145045965</bin>
      </cell>
      <cell lat='39.5' lon='140.6'>
        <bin m='3.0'>0.00102145045965</bin>
      </cell>
      <cell lat='39.6' lon='140.6'>
        <bin m='3.0'>0.00102145045965</bin>
      </cell>
      <cell lat='39.7' lon='140.6'>
        <bin m='3.0'>0.0122574055158</bin>
      </cell>
      <cell lat='39.8' lon='140.6'>
        <bin m='3.0'>0.00612870275792</bin>
      </cell>
      <cell lat='39.9' lon='140.6'>
        <bin m='3.0'>0.00102145045965</bin>
      </cell>
      <cell lat='40.0' lon='140.6'>
        <bin m='3.0'>0.00102145045965</bin>
      </cell>
      <cell lat='40.1' lon='140.6'>
        <bin m='3.0'>0.00102145045965</bin>
      </cell>
      <cell lat='40.2' lon='140.6'>
        <bin m='3.0'>0.00102145045965</bin>
      </cell>
      <cell lat='40.3' lon='140.6'>
        <bin m='3.0'>0.00102145045965</bin>
      </cell>
      <cell lat='40.4' lon='140.6'>
        <bin m='3.0'>0.00102145045965</bin>
      </cell>
      <cell lat='40.5' lon='140.6'>
        <bin m='3.0'>0.00102145045965</bin>
      </cell>
      <cell lat='40.6' lon='140.6'>
        <bin m='3.0'>0.00102145045965</bin>
      </cell>
      <cell lat='40.7' lon='140.6'>
        <bin m='3.0'>0.00102145045965</bin>
      </cell>
      <cell lat='40.8' lon='140.6'>
        <bin m='3.0'>0.00919305413687</bin>
      </cell>
      <cell lat='40.9' lon='140.6'>
        <bin m='3.0'>0.00102145045965</bin>
      </cell>
      <cell lat='37.0' lon='140.7'>
        <bin m='3.0'>0.00102145045965</bin>
      </cell>
      <cell lat='37.1' lon='140.7'>
        <bin m='3.0'>0.00102145045965</bin>
      </cell>
      <cell lat='37.2' lon='140.7'>
        <bin m='3.0'>0.00102145045965</bin>
      </cell>
      <cell lat='37.3' lon='140.7'>
        <bin m='3.0'>0.00102145045965</bin>
      </cell>
      <cell lat='37.4' lon='140.7'>
        <bin m='3.0'>0.00102145045965</bin>
      </cell>
      <cell lat='37.5' lon='140.7'>
        <bin m='3.0'>0.00102145045965</bin>
      </cell>
      <cell lat='37.6' lon='140.7'>
        <bin m='3.0'>0.00102145045965</bin>
      </cell>
      <cell lat='37.7' lon='140.7'>
        <bin m='3.0'>0.00102145045965</bin>
      </cell>
      <cell lat='37.8' lon='140.7'>
        <bin m='3.0'>0.00102145045965</bin>
      </cell>
      <cell lat='37.9' lon='140.7'>
        <bin m='3.0'>0.00102145045965</bin>
      </cell>
      <cell lat='38.0' lon='140.7'>
        <bin m='3.0'>0.00102145045965</bin>
      </cell>
      <cell lat='38.1' lon='140.7'>
        <bin m='3.0'>0.00408580183861</bin>
      </cell>
      <cell lat='38.2' lon='140.7'>
        <bin m='3.0'>0.00102145045965</bin>
      </cell>
      <cell lat='38.3' lon='140.7'>
        <bin m='3.0'>0.00102145045965</bin>
      </cell>
      <cell lat='38.4' lon='140.7'>
        <bin m='3.0'>0.00306435137896</bin>
      </cell>
      <cell lat='38.5' lon='140.7'>
        <bin m='3.0'>0.00102145045965</bin>
      </cell>
      <cell lat='38.6' lon='140.7'>
        <bin m='3.0'>0.00102145045965</bin>
      </cell>
      <cell lat='38.7' lon='140.7'>
        <bin m='3.0'>0.00612870275792</bin>
      </cell>
      <cell lat='38.8' lon='140.7'>
        <bin m='3.0'>0.00612870275792</bin>
      </cell>
      <cell lat='38.9' lon='140.7'>
        <bin m='3.0'>0.00306435137896</bin>
      </cell>
      <cell lat='39.0' lon='140.7'>
        <bin m='3.0'>0.00102145045965</bin>
      </cell>
      <cell lat='39.1' lon='140.7'>
        <bin m='3.0'>0.00102145045965</bin>
      </cell>
      <cell lat='39.2' lon='140.7'>
        <bin m='3.0'>0.00102145045965</bin>
      </cell>
      <cell lat='39.3' lon='140.7'>
        <bin m='3.0'>0.00102145045965</bin>
      </cell>
      <cell lat='39.4' lon='140.7'>
        <bin m='3.0'>0.00102145045965</bin>
      </cell>
      <cell lat='39.5' lon='140.7'>
        <bin m='3.0'>0.00102145045965</bin>
      </cell>
      <cell lat='39.6' lon='140.7'>
        <bin m='3.0'>0.00102145045965</bin>
      </cell>
      <cell lat='39.7' lon='140.7'>
        <bin m='3.0'>0.00102145045965</bin>
      </cell>
      <cell lat='39.8' lon='140.7'>
        <bin m='3.0'>0.00102145045965</bin>
      </cell>
      <cell lat='39.9' lon='140.7'>
        <bin m='3.0'>0.00102145045965</bin>
      </cell>
      <cell lat='40.0' lon='140.7'>
        <bin m='3.0'>0.00102145045965</bin>
      </cell>
      <cell lat='40.1' lon='140.7'>
        <bin m='3.0'>0.0112359550562</bin>
      </cell>
      <cell lat='40.2' lon='140.7'>
        <bin m='3.0'>0.00919305413687</bin>
      </cell>
      <cell lat='40.3' lon='140.7'>
        <bin m='3.0'>0.00102145045965</bin>
      </cell>
      <cell lat='40.4' lon='140.7'>
        <bin m='3.0'>0.00102145045965</bin>
      </cell>
      <cell lat='40.5' lon='140.7'>
        <bin m='3.0'>0.00102145045965</bin>
      </cell>
      <cell lat='40.6' lon='140.7'>
        <bin m='3.0'>0.00102145045965</bin>
      </cell>
      <cell lat='40.7' lon='140.7'>
        <bin m='3.0'>0.00102145045965</bin>
      </cell>
      <cell lat='40.8' lon='140.7'>
        <bin m='3.0'>0.00102145045965</bin>
      </cell>
      <cell lat='40.9' lon='140.7'>
        <bin m='3.0'>0.00102145045965</bin>
      </cell>
      <cell lat='37.0' lon='140.8'>
        <bin m='3.0'>0.00102145045965</bin>
      </cell>
      <cell lat='37.1' lon='140.8'>
        <bin m='3.0'>0.00612870275792</bin>
      </cell>
      <cell lat='37.2' lon='140.8'>
        <bin m='3.0'>0.00102145045965</bin>
      </cell>
      <cell lat='37.3' lon='140.8'>
        <bin m='3.0'>0.00102145045965</bin>
      </cell>
      <cell lat='37.4' lon='140.8'>
        <bin m='3.0'>0.00510725229826</bin>
      </cell>
      <cell lat='37.5' lon='140.8'>
        <bin m='3.0'>0.00102145045965</bin>
      </cell>
      <cell lat='37.6' lon='140.8'>
        <bin m='3.0'>0.00102145045965</bin>
      </cell>
      <cell lat='37.7' lon='140.8'>
        <bin m='3.0'>0.00102145045965</bin>
      </cell>
      <cell lat='37.8' lon='140.8'>
        <bin m='3.0'>0.00204290091931</bin>
      </cell>
      <cell lat='37.9' lon='140.8'>
        <bin m='3.0'>0.00102145045965</bin>
      </cell>
      <cell lat='38.0' lon='140.8'>
        <bin m='3.0'>0.00102145045965</bin>
      </cell>
      <cell lat='38.1' lon='140.8'>
        <bin m='3.0'>0.00102145045965</bin>
      </cell>
      <cell lat='38.2' lon='140.8'>
        <bin m='3.0'>0.00102145045965</bin>
      </cell>
      <cell lat='38.3' lon='140.8'>
        <bin m='3.0'>0.00102145045965</bin>
      </cell>
      <cell lat='38.4' lon='140.8'>
        <bin m='3.0'>0.00102145045965</bin>
      </cell>
      <cell lat='38.5' lon='140.8'>
        <bin m='3.0'>0.00102145045965</bin>
      </cell>
      <cell lat='38.6' lon='140.8'>
        <bin m='3.0'>0.00102145045965</bin>
      </cell>
      <cell lat='38.7' lon='140.8'>
        <bin m='3.0'>0.00102145045965</bin>
      </cell>
      <cell lat='38.8' lon='140.8'>
        <bin m='3.0'>0.0122574055158</bin>
      </cell>
      <cell lat='38.9' lon='140.8'>
        <bin m='3.0'>0.00102145045965</bin>
      </cell>
      <cell lat='39.0' lon='140.8'>
        <bin m='3.0'>0.00102145045965</bin>
      </cell>
      <cell lat='39.1' lon='140.8'>
        <bin m='3.0'>0.00102145045965</bin>
      </cell>
      <cell lat='39.2' lon='140.8'>
        <bin m='3.0'>0.00102145045965</bin>
      </cell>
      <cell lat='39.3' lon='140.8'>
        <bin m='3.0'>0.00102145045965</bin>
      </cell>
      <cell lat='39.4' lon='140.8'>
        <bin m='3.0'>0.00102145045965</bin>
      </cell>
      <cell lat='39.5' lon='140.8'>
        <bin m='3.0'>0.00102145045965</bin>
      </cell>
      <cell lat='39.6' lon='140.8'>
        <bin m='3.0'>0.00102145045965</bin>
      </cell>
      <cell lat='39.7' lon='140.8'>
        <bin m='3.0'>0.00102145045965</bin>
      </cell>
      <cell lat='39.8' lon='140.8'>
        <bin m='3.0'>0.00102145045965</bin>
      </cell>
      <cell lat='39.9' lon='140.8'>
        <bin m='3.0'>0.00102145045965</bin>
      </cell>
      <cell lat='40.0' lon='140.8'>
        <bin m='3.0'>0.00102145045965</bin>
      </cell>
      <cell lat='40.1' lon='140.8'>
        <bin m='3.0'>0.00102145045965</bin>
      </cell>
      <cell lat='40.2' lon='140.8'>
        <bin m='3.0'>0.00102145045965</bin>
      </cell>
      <cell lat='40.3' lon='140.8'>
        <bin m='3.0'>0.00102145045965</bin>
      </cell>
      <cell lat='40.4' lon='140.8'>
        <bin m='3.0'>0.00102145045965</bin>
      </cell>
      <cell lat='40.5' lon='140.8'>
        <bin m='3.0'>0.00102145045965</bin>
      </cell>
      <cell lat='40.6' lon='140.8'>
        <bin m='3.0'>0.00102145045965</bin>
      </cell>
      <cell lat='40.7' lon='140.8'>
        <bin m='3.0'>0.00102145045965</bin>
      </cell>
      <cell lat='40.8' lon='140.8'>
        <bin m='3.0'>0.00102145045965</bin>
      </cell>
      <cell lat='40.9' lon='140.8'>
        <bin m='3.0'>0.00102145045965</bin>
      </cell>
      <cell lat='37.0' lon='140.9'>
        <bin m='3.0'>0.00102145045965</bin>
      </cell>
      <cell lat='37.1' lon='140.9'>
        <bin m='3.0'>0.00102145045965</bin>
      </cell>
      <cell lat='37.2' lon='140.9'>
        <bin m='3.0'>0.00102145045965</bin>
      </cell>
      <cell lat='37.3' lon='140.9'>
        <bin m='3.0'>0.00102145045965</bin>
      </cell>
      <cell lat='37.4' lon='140.9'>
        <bin m='3.0'>0.00102145045965</bin>
      </cell>
      <cell lat='37.5' lon='140.9'>
        <bin m='3.0'>0.00102145045965</bin>
      </cell>
      <cell lat='37.6' lon='140.9'>
        <bin m='3.0'>0.00102145045965</bin>
      </cell>
      <cell lat='37.7' lon='140.9'>
        <bin m='3.0'>0.00102145045965</bin>
      </cell>
      <cell lat='37.8' lon='140.9'>
        <bin m='3.0'>0.00102145045965</bin>
      </cell>
      <cell lat='37.9' lon='140.9'>
        <bin m='3.0'>0.00102145045965</bin>
      </cell>
      <cell lat='38.0' lon='140.9'>
        <bin m='3.0'>0.00102145045965</bin>
      </cell>
      <cell lat='38.1' lon='140.9'>
        <bin m='3.0'>0.00102145045965</bin>
      </cell>
      <cell lat='38.2' lon='140.9'>
        <bin m='3.0'>0.00102145045965</bin>
      </cell>
      <cell lat='38.3' lon='140.9'>
        <bin m='3.0'>0.00102145045965</bin>
      </cell>
      <cell lat='38.4' lon='140.9'>
        <bin m='3.0'>0.00102145045965</bin>
      </cell>
      <cell lat='38.5' lon='140.9'>
        <bin m='3.0'>0.00102145045965</bin>
      </cell>
      <cell lat='38.6' lon='140.9'>
        <bin m='3.0'>0.00102145045965</bin>
      </cell>
      <cell lat='38.7' lon='140.9'>
        <bin m='3.0'>0.00102145045965</bin>
      </cell>
      <cell lat='38.8' lon='140.9'>
        <bin m='3.0'>0.00102145045965</bin>
      </cell>
      <cell lat='38.9' lon='140.9'>
        <bin m='3.0'>0.00102145045965</bin>
      </cell>
      <cell lat='39.0' lon='140.9'>
        <bin m='3.0'>0.00102145045965</bin>
      </cell>
      <cell lat='39.1' lon='140.9'>
        <bin m='3.0'>0.00102145045965</bin>
      </cell>
      <cell lat='39.2' lon='140.9'>
        <bin m='3.0'>0.00102145045965</bin>
      </cell>
      <cell lat='39.3' lon='140.9'>
        <bin m='3.0'>0.00102145045965</bin>
      </cell>
      <cell lat='39.4' lon='140.9'>
        <bin m='3.0'>0.00102145045965</bin>
      </cell>
      <cell lat='39.5' lon='140.9'>
        <bin m='3.0'>0.00306435137896</bin>
      </cell>
      <cell lat='39.6' lon='140.9'>
        <bin m='3.0'>0.00102145045965</bin>
      </cell>
      <cell lat='39.7' lon='140.9'>
        <bin m='3.0'>0.00102145045965</bin>
      </cell>
      <cell lat='39.8' lon='140.9'>
        <bin m='3.0'>0.00102145045965</bin>
      </cell>
      <cell lat='39.9' lon='140.9'>
        <bin m='3.0'>0.00102145045965</bin>
      </cell>
      <cell lat='40.0' lon='140.9'>
        <bin m='3.0'>0.00102145045965</bin>
      </cell>
      <cell lat='40.1' lon='140.9'>
        <bin m='3.0'>0.00102145045965</bin>
      </cell>
      <cell lat='40.2' lon='140.9'>
        <bin m='3.0'>0.00102145045965</bin>
      </cell>
      <cell lat='40.3' lon='140.9'>
        <bin m='3.0'>0.00102145045965</bin>
      </cell>
      <cell lat='40.4' lon='140.9'>
        <bin m='3.0'>0.00102145045965</bin>
      </cell>
      <cell lat='40.5' lon='140.9'>
        <bin m='3.0'>0.00102145045965</bin>
      </cell>
      <cell lat='40.6' lon='140.9'>
        <bin m='3.0'>0.00102145045965</bin>
      </cell>
      <cell lat='40.7' lon='140.9'>
        <bin m='3.0'>0.00102145045965</bin>
      </cell>
      <cell lat='40.8' lon='140.9'>
        <bin m='3.0'>0.00102145045965</bin>
      </cell>
      <cell lat='40.9' lon='140.9'>
        <bin m='3.0'>0.00102145045965</bin>
      </cell>
      <cell lat='37.0' lon='141.0'>
        <bin m='3.0'>0.00102145045965</bin>
      </cell>
      <cell lat='37.1' lon='141.0'>
        <bin m='3.0'>0.00102145045965</bin>
      </cell>
      <cell lat='37.2' lon='141.0'>
        <bin m='3.0'>0.00102145045965</bin>
      </cell>
      <cell lat='37.3' lon='141.0'>
        <bin m='3.0'>0.00102145045965</bin>
      </cell>
      <cell lat='37.4' lon='141.0'>
        <bin m='3.0'>0.00102145045965</bin>
      </cell>
      <cell lat='37.5' lon='141.0'>
        <bin m='3.0'>0.00102145045965</bin>
      </cell>
      <cell lat='37.6' lon='141.0'>
        <bin m='3.0'>0.00102145045965</bin>
      </cell>
      <cell lat='37.7' lon='141.0'>
        <bin m='3.0'>0.00102145045965</bin>
      </cell>
      <cell lat='37.8' lon='141.0'>
        <bin m='3.0'>0.00102145045965</bin>
      </cell>
      <cell lat='37.9' lon='141.0'>
        <bin m='3.0'>0.00102145045965</bin>
      </cell>
      <cell lat='38.0' lon='141.0'>
        <bin m='3.0'>0.00102145045965</bin>
      </cell>
      <cell lat='38.1' lon='141.0'>
        <bin m='3.0'>0.00102145045965</bin>
      </cell>
      <cell lat='38.2' lon='141.0'>
        <bin m='3.0'>0.00102145045965</bin>
      </cell>
      <cell lat='38.3' lon='141.0'>
        <bin m='3.0'>0.00102145045965</bin>
      </cell>
      <cell lat='38.4' lon='141.0'>
        <bin m='3.0'>0.00102145045965</bin>
      </cell>
      <cell lat='38.5' lon='141.0'>
        <bin m='3.0'>0.00102145045965</bin>
      </cell>
      <cell lat='38.6' lon='141.0'>
        <bin m='3.0'>0.00102145045965</bin>
      </cell>
      <cell lat='38.7' lon='141.0'>
        <bin m='3.0'>0.00102145045965</bin>
      </cell>
      <cell lat='38.8' lon='141.0'>
        <bin m='3.0'>0.00102145045965</bin>
      </cell>
      <cell lat='38.9' lon='141.0'>
        <bin m='3.0'>0.00102145045965</bin>
      </cell>
      <cell lat='39.0' lon='141.0'>
        <bin m='3.0'>0.00102145045965</bin>
      </cell>
      <cell lat='39.1' lon='141.0'>
        <bin m='3.0'>0.00102145045965</bin>
      </cell>
      <cell lat='39.2' lon='141.0'>
        <bin m='3.0'>0.00102145045965</bin>
      </cell>
      <cell lat='39.3' lon='141.0'>
        <bin m='3.0'>0.00102145045965</bin>
      </cell>
      <cell lat='39.4' lon='141.0'>
        <bin m='3.0'>0.00102145045965</bin>
      </cell>
      <cell lat='39.5' lon='141.0'>
        <bin m='3.0'>0.00102145045965</bin>
      </cell>
      <cell lat='39.6' lon='141.0'>
        <bin m='3.0'>0.00102145045965</bin>
      </cell>
      <cell lat='39.7' lon='141.0'>
        <bin m='3.0'>0.00102145045965</bin>
      </cell>
      <cell lat='39.8' lon='141.0'>
        <bin m='3.0'>0.00102145045965</bin>
      </cell>
      <cell lat='39.9' lon='141.0'>
        <bin m='3.0'>0.00102145045965</bin>
      </cell>
      <cell lat='40.0' lon='141.0'>
        <bin m='3.0'>0.00102145045965</bin>
      </cell>
      <cell lat='40.1' lon='141.0'>
        <bin m='3.0'>0.00102145045965</bin>
      </cell>
      <cell lat='40.2' lon='141.0'>
        <bin m='3.0'>0.00102145045965</bin>
      </cell>
      <cell lat='40.3' lon='141.0'>
        <bin m='3.0'>0.00102145045965</bin>
      </cell>
      <cell lat='40.4' lon='141.0'>
        <bin m='3.0'>0.00102145045965</bin>
      </cell>
      <cell lat='40.5' lon='141.0'>
        <bin m='3.0'>0.00102145045965</bin>
      </cell>
      <cell lat='40.6' lon='141.0'>
        <bin m='3.0'>0.00102145045965</bin>
      </cell>
      <cell lat='40.7' lon='141.0'>
        <bin m='3.0'>0.00102145045965</bin>
      </cell>
      <cell lat='40.8' lon='141.0'>
        <bin m='3.0'>0.00102145045965</bin>
      </cell>
      <cell lat='40.9' lon='141.0'>
        <bin m='3.0'>0.00102145045965</bin>
      </cell>
      <cell lat='37.0' lon='141.1'>
        <bin m='3.0'>0.00102145045965</bin>
      </cell>
      <cell lat='37.1' lon='141.1'>
        <bin m='3.0'>0.00102145045965</bin>
      </cell>
      <cell lat='37.2' lon='141.1'>
        <bin m='3.0'>0.00102145045965</bin>
      </cell>
      <cell lat='37.3' lon='141.1'>
        <bin m='3.0'>0.00102145045965</bin>
      </cell>
      <cell lat='37.4' lon='141.1'>
        <bin m='3.0'>0.00102145045965</bin>
      </cell>
      <cell lat='37.5' lon='141.1'>
        <bin m='3.0'>0.00102145045965</bin>
      </cell>
      <cell lat='37.6' lon='141.1'>
        <bin m='3.0'>0.00102145045965</bin>
      </cell>
      <cell lat='37.7' lon='141.1'>
        <bin m='3.0'>0.00102145045965</bin>
      </cell>
      <cell lat='37.8' lon='141.1'>
        <bin m='3.0'>0.00102145045965</bin>
      </cell>
      <cell lat='37.9' lon='141.1'>
        <bin m='3.0'>0.00102145045965</bin>
      </cell>
      <cell lat='38.0' lon='141.1'>
        <bin m='3.0'>0.00102145045965</bin>
      </cell>
      <cell lat='38.1' lon='141.1'>
        <bin m='3.0'>0.00102145045965</bin>
      </cell>
      <cell lat='38.2' lon='141.1'>
        <bin m='3.0'>0.00102145045965</bin>
      </cell>
      <cell lat='38.3' lon='141.1'>
        <bin m='3.0'>0.00102145045965</bin>
      </cell>
      <cell lat='38.4' lon='141.1'>
        <bin m='3.0'>0.00102145045965</bin>
      </cell>
      <cell lat='38.5' lon='141.1'>
        <bin m='3.0'>0.00102145045965</bin>
      </cell>
      <cell lat='38.6' lon='141.1'>
        <bin m='3.0'>0.00102145045965</bin>
      </cell>
      <cell lat='38.7' lon='141.1'>
        <bin m='3.0'>0.00102145045965</bin>
      </cell>
      <cell lat='38.8' lon='141.1'>
        <bin m='3.0'>0.00102145045965</bin>
      </cell>
      <cell lat='38.9' lon='141.1'>
        <bin m='3.0'>0.00102145045965</bin>
      </cell>
      <cell lat='39.0' lon='141.1'>
        <bin m='3.0'>0.00102145045965</bin>
      </cell>
      <cell lat='39.1' lon='141.1'>
        <bin m='3.0'>0.00102145045965</bin>
      </cell>
      <cell lat='39.2' lon='141.1'>
        <bin m='3.0'>0.00102145045965</bin>
      </cell>
      <cell lat='39.3' lon='141.1'>
        <bin m='3.0'>0.00102145045965</bin>
      </cell>
      <cell lat='39.4' lon='141.1'>
        <bin m='3.0'>0.00102145045965</bin>
      </cell>
      <cell lat='39.5' lon='141.1'>
        <bin m='3.0'>0.00102145045965</bin>
      </cell>
      <cell lat='39.6' lon='141.1'>
        <bin m='3.0'>0.00102145045965</bin>
      </cell>
      <cell lat='39.7' lon='141.1'>
        <bin m='3.0'>0.00102145045965</bin>
      </cell>
      <cell lat='39.8' lon='141.1'>
        <bin m='3.0'>0.00102145045965</bin>
      </cell>
      <cell lat='39.9' lon='141.1'>
        <bin m='3.0'>0.00102145045965</bin>
      </cell>
      <cell lat='40.0' lon='141.1'>
        <bin m='3.0'>0.00102145045965</bin>
      </cell>
      <cell lat='40.1' lon='141.1'>
        <bin m='3.0'>0.00102145045965</bin>
      </cell>
      <cell lat='40.2' lon='141.1'>
        <bin m='3.0'>0.00102145045965</bin>
      </cell>
      <cell lat='40.3' lon='141.1'>
        <bin m='3.0'>0.00102145045965</bin>
      </cell>
      <cell lat='40.4' lon='141.1'>
        <bin m='3.0'>0.00102145045965</bin>
      </cell>
      <cell lat='40.5' lon='141.1'>
        <bin m='3.0'>0.00102145045965</bin>
      </cell>
      <cell lat='40.6' lon='141.1'>
        <bin m='3.0'>0.00102145045965</bin>
      </cell>
      <cell lat='40.7' lon='141.1'>
        <bin m='3.0'>0.00102145045965</bin>
      </cell>
      <cell lat='40.8' lon='141.1'>
        <bin m='3.0'>0.00102145045965</bin>
      </cell>
      <cell lat='40.9' lon='141.1'>
        <bin m='3.0'>0.00102145045965</bin>
      </cell>
      <cell lat='37.0' lon='141.2'>
        <bin m='3.0'>0.00102145045965</bin>
      </cell>
      <cell lat='37.1' lon='141.2'>
        <bin m='3.0'>0.00102145045965</bin>
      </cell>
      <cell lat='37.2' lon='141.2'>
        <bin m='3.0'>0.00102145045965</bin>
      </cell>
      <cell lat='37.3' lon='141.2'>
        <bin m='3.0'>0.00102145045965</bin>
      </cell>
      <cell lat='37.4' lon='141.2'>
        <bin m='3.0'>0.00102145045965</bin>
      </cell>
      <cell lat='37.5' lon='141.2'>
        <bin m='3.0'>0.00102145045965</bin>
      </cell>
      <cell lat='37.6' lon='141.2'>
        <bin m='3.0'>0.00102145045965</bin>
      </cell>
      <cell lat='37.7' lon='141.2'>
        <bin m='3.0'>0.00102145045965</bin>
      </cell>
      <cell lat='37.8' lon='141.2'>
        <bin m='3.0'>0.00102145045965</bin>
      </cell>
      <cell lat='37.9' lon='141.2'>
        <bin m='3.0'>0.00102145045965</bin>
      </cell>
      <cell lat='38.0' lon='141.2'>
        <bin m='3.0'>0.00102145045965</bin>
      </cell>
      <cell lat='38.1' lon='141.2'>
        <bin m='3.0'>0.00102145045965</bin>
      </cell>
      <cell lat='38.2' lon='141.2'>
        <bin m='3.0'>0.00102145045965</bin>
      </cell>
      <cell lat='38.3' lon='141.2'>
        <bin m='3.0'>0.00102145045965</bin>
      </cell>
      <cell lat='38.4' lon='141.2'>
        <bin m='3.0'>0.00102145045965</bin>
      </cell>
      <cell lat='38.5' lon='141.2'>
        <bin m='3.0'>0.00102145045965</bin>
      </cell>
      <cell lat='38.6' lon='141.2'>
        <bin m='3.0'>0.00102145045965</bin>
      </cell>
      <cell lat='38.7' lon='141.2'>
        <bin m='3.0'>0.00102145045965</bin>
      </cell>
      <cell lat='38.8' lon='141.2'>
        <bin m='3.0'>0.00102145045965</bin>
      </cell>
      <cell lat='38.9' lon='141.2'>
        <bin m='3.0'>0.00102145045965</bin>
      </cell>
      <cell lat='39.0' lon='141.2'>
        <bin m='3.0'>0.00102145045965</bin>
      </cell>
      <cell lat='39.1' lon='141.2'>
        <bin m='3.0'>0.00102145045965</bin>
      </cell>
      <cell lat='39.2' lon='141.2'>
        <bin m='3.0'>0.00102145045965</bin>
      </cell>
      <cell lat='39.3' lon='141.2'>
        <bin m='3.0'>0.00102145045965</bin>
      </cell>
      <cell lat='39.4' lon='141.2'>
        <bin m='3.0'>0.00102145045965</bin>
      </cell>
      <cell lat='39.5' lon='141.2'>
        <bin m='3.0'>0.00102145045965</bin>
      </cell>
      <cell lat='39.6' lon='141.2'>
        <bin m='3.0'>0.00102145045965</bin>
      </cell>
      <cell lat='39.7' lon='141.2'>
        <bin m='3.0'>0.00102145045965</bin>
      </cell>
      <cell lat='39.8' lon='141.2'>
        <bin m='3.0'>0.00102145045965</bin>
      </cell>
      <cell lat='39.9' lon='141.2'>
        <bin m='3.0'>0.00102145045965</bin>
      </cell>
      <cell lat='40.0' lon='141.2'>
        <bin m='3.0'>0.00102145045965</bin>
      </cell>
      <cell lat='40.1' lon='141.2'>
        <bin m='3.0'>0.00102145045965</bin>
      </cell>
      <cell lat='40.2' lon='141.2'>
        <bin m='3.0'>0.00102145045965</bin>
      </cell>
      <cell lat='40.3' lon='141.2'>
        <bin m='3.0'>0.00102145045965</bin>
      </cell>
      <cell lat='40.4' lon='141.2'>
        <bin m='3.0'>0.00102145045965</bin>
      </cell>
      <cell lat='40.5' lon='141.2'>
        <bin m='3.0'>0.00102145045965</bin>
      </cell>
      <cell lat='40.6' lon='141.2'>
        <bin m='3.0'>0.00102145045965</bin>
      </cell>
      <cell lat='40.7' lon='141.2'>
        <bin m='3.0'>0.00102145045965</bin>
      </cell>
      <cell lat='40.8' lon='141.2'>
        <bin m='3.0'>0.00102145045965</bin>
      </cell>
      <cell lat='40.9' lon='141.2'>
        <bin m='3.0'>0.00102145045965</bin>
      </cell>
      <cell lat='37.0' lon='141.3'>
        <bin m='3.0'>0.00102145045965</bin>
      </cell>
      <cell lat='37.1' lon='141.3'>
        <bin m='3.0'>0.00102145045965</bin>
      </cell>
      <cell lat='37.2' lon='141.3'>
        <bin m='3.0'>0.00102145045965</bin>
      </cell>
      <cell lat='37.3' lon='141.3'>
        <bin m='3.0'>0.00102145045965</bin>
      </cell>
      <cell lat='37.4' lon='141.3'>
        <bin m='3.0'>0.00102145045965</bin>
      </cell>
      <cell lat='37.5' lon='141.3'>
        <bin m='3.0'>0.00102145045965</bin>
      </cell>
      <cell lat='37.6' lon='141.3'>
        <bin m='3.0'>0.00102145045965</bin>
      </cell>
      <cell lat='37.7' lon='141.3'>
        <bin m='3.0'>0.00102145045965</bin>
      </cell>
      <cell lat='37.8' lon='141.3'>
        <bin m='3.0'>0.00102145045965</bin>
      </cell>
      <cell lat='37.9' lon='141.3'>
        <bin m='3.0'>0.00102145045965</bin>
      </cell>
      <cell lat='38.0' lon='141.3'>
        <bin m='3.0'>0.00102145045965</bin>
      </cell>
      <cell lat='38.1' lon='141.3'>
        <bin m='3.0'>0.00102145045965</bin>
      </cell>
      <cell lat='38.2' lon='141.3'>
        <bin m='3.0'>0.00102145045965</bin>
      </cell>
      <cell lat='38.3' lon='141.3'>
        <bin m='3.0'>0.00102145045965</bin>
      </cell>
      <cell lat='38.4' lon='141.3'>
        <bin m='3.0'>0.00102145045965</bin>
      </cell>
      <cell lat='38.5' lon='141.3'>
        <bin m='3.0'>0.00102145045965</bin>
      </cell>
      <cell lat='38.6' lon='141.3'>
        <bin m='3.0'>0.00102145045965</bin>
      </cell>
      <cell lat='38.7' lon='141.3'>
        <bin m='3.0'>0.00102145045965</bin>
      </cell>
      <cell lat='38.8' lon='141.3'>
        <bin m='3.0'>0.00102145045965</bin>
      </cell>
      <cell lat='38.9' lon='141.3'>
        <bin m='3.0'>0.00102145045965</bin>
      </cell>
      <cell lat='39.0' lon='141.3'>
        <bin m='3.0'>0.00102145045965</bin>
      </cell>
      <cell lat='39.1' lon='141.3'>
        <bin m='3.0'>0.00102145045965</bin>
      </cell>
      <cell lat='39.2' lon='141.3'>
        <bin m='3.0'>0.00102145045965</bin>
      </cell>
      <cell lat='39.3' lon='141.3'>
        <bin m='3.0'>0.00102145045965</bin>
      </cell>
      <cell lat='39.4' lon='141.3'>
        <bin m='3.0'>0.00102145045965</bin>
      </cell>
      <cell lat='39.5' lon='141.3'>
        <bin m='3.0'>0.00102145045965</bin>
      </cell>
      <cell lat='39.6' lon='141.3'>
        <bin m='3.0'>0.00102145045965</bin>
      </cell>
      <cell lat='39.7' lon='141.3'>
        <bin m='3.0'>0.00102145045965</bin>
      </cell>
      <cell lat='39.8' lon='141.3'>
        <bin m='3.0'>0.00102145045965</bin>
      </cell>
      <cell lat='39.9' lon='141.3'>
        <bin m='3.0'>0.00102145045965</bin>
      </cell>
      <cell lat='40.0' lon='141.3'>
        <bin m='3.0'>0.00102145045965</bin>
      </cell>
      <cell lat='40.1' lon='141.3'>
        <bin m='3.0'>0.00102145045965</bin>
      </cell>
      <cell lat='40.2' lon='141.3'>
        <bin m='3.0'>0.00102145045965</bin>
      </cell>
      <cell lat='40.3' lon='141.3'>
        <bin m='3.0'>0.00102145045965</bin>
      </cell>
      <cell lat='40.4' lon='141.3'>
        <bin m='3.0'>0.00102145045965</bin>
      </cell>
      <cell lat='40.5' lon='141.3'>
        <bin m='3.0'>0.00102145045965</bin>
      </cell>
      <cell lat='40.6' lon='141.3'>
        <bin m='3.0'>0.00102145045965</bin>
      </cell>
      <cell lat='40.7' lon='141.3'>
        <bin m='3.0'>0.00102145045965</bin>
      </cell>
      <cell lat='40.8' lon='141.3'>
        <bin m='3.0'>0.00102145045965</bin>
      </cell>
      <cell lat='40.9' lon='141.3'>
        <bin m='3.0'>0.00102145045965</bin>
      </cell>
      <cell lat='37.0' lon='141.4'>
        <bin m='3.0'>0.00102145045965</bin>
      </cell>
      <cell lat='37.1' lon='141.4'>
        <bin m='3.0'>0.00102145045965</bin>
      </cell>
      <cell lat='37.2' lon='141.4'>
        <bin m='3.0'>0.00102145045965</bin>
      </cell>
      <cell lat='37.3' lon='141.4'>
        <bin m='3.0'>0.00102145045965</bin>
      </cell>
      <cell lat='37.4' lon='141.4'>
        <bin m='3.0'>0.00102145045965</bin>
      </cell>
      <cell lat='37.5' lon='141.4'>
        <bin m='3.0'>0.00102145045965</bin>
      </cell>
      <cell lat='37.6' lon='141.4'>
        <bin m='3.0'>0.00102145045965</bin>
      </cell>
      <cell lat='37.7' lon='141.4'>
        <bin m='3.0'>0.00102145045965</bin>
      </cell>
      <cell lat='37.8' lon='141.4'>
        <bin m='3.0'>0.00102145045965</bin>
      </cell>
      <cell lat='37.9' lon='141.4'>
        <bin m='3.0'>0.00102145045965</bin>
      </cell>
      <cell lat='38.0' lon='141.4'>
        <bin m='3.0'>0.00102145045965</bin>
      </cell>
      <cell lat='38.1' lon='141.4'>
        <bin m='3.0'>0.00102145045965</bin>
      </cell>
      <cell lat='38.2' lon='141.4'>
        <bin m='3.0'>0.00102145045965</bin>
      </cell>
      <cell lat='38.3' lon='141.4'>
        <bin m='3.0'>0.00102145045965</bin>
      </cell>
      <cell lat='38.4' lon='141.4'>
        <bin m='3.0'>0.00102145045965</bin>
      </cell>
      <cell lat='38.5' lon='141.4'>
        <bin m='3.0'>0.00102145045965</bin>
      </cell>
      <cell lat='38.6' lon='141.4'>
        <bin m='3.0'>0.00102145045965</bin>
      </cell>
      <cell lat='38.7' lon='141.4'>
        <bin m='3.0'>0.00102145045965</bin>
      </cell>
      <cell lat='38.8' lon='141.4'>
        <bin m='3.0'>0.00102145045965</bin>
      </cell>
      <cell lat='38.9' lon='141.4'>
        <bin m='3.0'>0.00102145045965</bin>
      </cell>
      <cell lat='39.0' lon='141.4'>
        <bin m='3.0'>0.00102145045965</bin>
      </cell>
      <cell lat='39.1' lon='141.4'>
        <bin m='3.0'>0.00102145045965</bin>
      </cell>
      <cell lat='39.2' lon='141.4'>
        <bin m='3.0'>0.00102145045965</bin>
      </cell>
      <cell lat='39.3' lon='141.4'>
        <bin m='3.0'>0.00102145045965</bin>
      </cell>
      <cell lat='39.4' lon='141.4'>
        <bin m='3.0'>0.00102145045965</bin>
      </cell>
      <cell lat='39.5' lon='141.4'>
        <bin m='3.0'>0.00102145045965</bin>
      </cell>
      <cell lat='39.6' lon='141.4'>
        <bin m='3.0'>0.00102145045965</bin>
      </cell>
      <cell lat='39.7' lon='141.4'>
        <bin m='3.0'>0.00102145045965</bin>
      </cell>
      <cell lat='39.8' lon='141.4'>
        <bin m='3.0'>0.00102145045965</bin>
      </cell>
      <cell lat='39.9' lon='141.4'>
        <bin m='3.0'>0.00102145045965</bin>
      </cell>
      <cell lat='40.0' lon='141.4'>
        <bin m='3.0'>0.00102145045965</bin>
      </cell>
      <cell lat='40.1' lon='141.4'>
        <bin m='3.0'>0.00408580183861</bin>
      </cell>
      <cell lat='40.2' lon='141.4'>
        <bin m='3.0'>0.00102145045965</bin>
      </cell>
      <cell lat='40.3' lon='141.4'>
        <bin m='3.0'>0.00102145045965</bin>
      </cell>
      <cell lat='40.4' lon='141.4'>
        <bin m='3.0'>0.00102145045965</bin>
      </cell>
      <cell lat='40.5' lon='141.4'>
        <bin m='3.0'>0.00102145045965</bin>
      </cell>
      <cell lat='40.6' lon='141.4'>
        <bin m='3.0'>0.00102145045965</bin>
      </cell>
      <cell lat='40.7' lon='141.4'>
        <bin m='3.0'>0.00102145045965</bin>
      </cell>
      <cell lat='40.8' lon='141.4'>
        <bin m='3.0'>0.00102145045965</bin>
      </cell>
      <cell lat='40.9' lon='141.4'>
        <bin m='3.0'>0.00102145045965</bin>
      </cell>
      <cell lat='37.0' lon='141.5'>
        <bin m='3.0'>0.00102145045965</bin>
      </cell>
      <cell lat='37.1' lon='141.5'>
        <bin m='3.0'>0.00102145045965</bin>
      </cell>
      <cell lat='37.2' lon='141.5'>
        <bin m='3.0'>0.00102145045965</bin>
      </cell>
      <cell lat='37.3' lon='141.5'>
        <bin m='3.0'>0.00102145045965</bin>
      </cell>
      <cell lat='37.4' lon='141.5'>
        <bin m='3.0'>0.00102145045965</bin>
      </cell>
      <cell lat='37.5' lon='141.5'>
        <bin m='3.0'>0.00102145045965</bin>
      </cell>
      <cell lat='37.6' lon='141.5'>
        <bin m='3.0'>0.00102145045965</bin>
      </cell>
      <cell lat='37.7' lon='141.5'>
        <bin m='3.0'>0.00102145045965</bin>
      </cell>
      <cell lat='37.8' lon='141.5'>
        <bin m='3.0'>0.00102145045965</bin>
      </cell>
      <cell lat='37.9' lon='141.5'>
        <bin m='3.0'>0.00102145045965</bin>
      </cell>
      <cell lat='38.0' lon='141.5'>
        <bin m='3.0'>0.00102145045965</bin>
      </cell>
      <cell lat='38.1' lon='141.5'>
        <bin m='3.0'>0.00102145045965</bin>
      </cell>
      <cell lat='38.2' lon='141.5'>
        <bin m='3.0'>0.00102145045965</bin>
      </cell>
      <cell lat='38.3' lon='141.5'>
        <bin m='3.0'>0.00102145045965</bin>
      </cell>
      <cell lat='38.4' lon='141.5'>
        <bin m='3.0'>0.00102145045965</bin>
      </cell>
      <cell lat='38.5' lon='141.5'>
        <bin m='3.0'>0.00102145045965</bin>
      </cell>
      <cell lat='38.6' lon='141.5'>
        <bin m='3.0'>0.00102145045965</bin>
      </cell>
      <cell lat='38.7' lon='141.5'>
        <bin m='3.0'>0.00102145045965</bin>
      </cell>
      <cell lat='38.8' lon='141.5'>
        <bin m='3.0'>0.00102145045965</bin>
      </cell>
      <cell lat='38.9' lon='141.5'>
        <bin m='3.0'>0.00102145045965</bin>
      </cell>
      <cell lat='39.0' lon='141.5'>
        <bin m='3.0'>0.00102145045965</bin>
      </cell>
      <cell lat='39.1' lon='141.5'>
        <bin m='3.0'>0.00102145045965</bin>
      </cell>
      <cell lat='39.2' lon='141.5'>
        <bin m='3.0'>0.00102145045965</bin>
      </cell>
      <cell lat='39.3' lon='141.5'>
        <bin m='3.0'>0.00102145045965</bin>
      </cell>
      <cell lat='39.4' lon='141.5'>
        <bin m='3.0'>0.00102145045965</bin>
      </cell>
      <cell lat='39.5' lon='141.5'>
        <bin m='3.0'>0.00102145045965</bin>
      </cell>
      <cell lat='39.6' lon='141.5'>
        <bin m='3.0'>0.00102145045965</bin>
      </cell>
      <cell lat='39.7' lon='141.5'>
        <bin m='3.0'>0.00102145045965</bin>
      </cell>
      <cell lat='39.8' lon='141.5'>
        <bin m='3.0'>0.00102145045965</bin>
      </cell>
      <cell lat='39.9' lon='141.5'>
        <bin m='3.0'>0.00102145045965</bin>
      </cell>
      <cell lat='40.0' lon='141.5'>
        <bin m='3.0'>0.00102145045965</bin>
      </cell>
      <cell lat='40.1' lon='141.5'>
        <bin m='3.0'>0.00102145045965</bin>
      </cell>
      <cell lat='40.2' lon='141.5'>
        <bin m='3.0'>0.00102145045965</bin>
      </cell>
      <cell lat='40.3' lon='141.5'>
        <bin m='3.0'>0.00102145045965</bin>
      </cell>
      <cell lat='40.4' lon='141.5'>
        <bin m='3.0'>0.00102145045965</bin>
      </cell>
      <cell lat='40.5' lon='141.5'>
        <bin m='3.0'>0.00102145045965</bin>
      </cell>
      <cell lat='40.6' lon='141.5'>
        <bin m='3.0'>0.00102145045965</bin>
      </cell>
      <cell lat='40.7' lon='141.5'>
        <bin m='3.0'>0.00102145045965</bin>
      </cell>
      <cell lat='40.8' lon='141.5'>
        <bin m='3.0'>0.00102145045965</bin>
      </cell>
      <cell lat='40.9' lon='141.5'>
        <bin m='3.0'>0.00102145045965</bin>
      </cell>
      <cell lat='37.0' lon='141.6'>
        <bin m='3.0'>0.00102145045965</bin>
      </cell>
      <cell lat='37.1' lon='141.6'>
        <bin m='3.0'>0.00102145045965</bin>
      </cell>
      <cell lat='37.2' lon='141.6'>
        <bin m='3.0'>0.00102145045965</bin>
      </cell>
      <cell lat='37.3' lon='141.6'>
        <bin m='3.0'>0.00102145045965</bin>
      </cell>
      <cell lat='37.4' lon='141.6'>
        <bin m='3.0'>0.00102145045965</bin>
      </cell>
      <cell lat='37.5' lon='141.6'>
        <bin m='3.0'>0.00102145045965</bin>
      </cell>
      <cell lat='37.6' lon='141.6'>
        <bin m='3.0'>0.00102145045965</bin>
      </cell>
      <cell lat='37.7' lon='141.6'>
        <bin m='3.0'>0.00102145045965</bin>
      </cell>
      <cell lat='37.8' lon='141.6'>
        <bin m='3.0'>0.00102145045965</bin>
      </cell>
      <cell lat='37.9' lon='141.6'>
        <bin m='3.0'>0.00102145045965</bin>
      </cell>
      <cell lat='38.0' lon='141.6'>
        <bin m='3.0'>0.00102145045965</bin>
      </cell>
      <cell lat='38.1' lon='141.6'>
        <bin m='3.0'>0.00102145045965</bin>
      </cell>
      <cell lat='38.2' lon='141.6'>
        <bin m='3.0'>0.00102145045965</bin>
      </cell>
      <cell lat='38.3' lon='141.6'>
        <bin m='3.0'>0.00102145045965</bin>
      </cell>
      <cell lat='38.4' lon='141.6'>
        <bin m='3.0'>0.00102145045965</bin>
      </cell>
      <cell lat='38.5' lon='141.6'>
        <bin m='3.0'>0.00102145045965</bin>
      </cell>
      <cell lat='38.6' lon='141.6'>
        <bin m='3.0'>0.00102145045965</bin>
      </cell>
      <cell lat='38.7' lon='141.6'>
        <bin m='3.0'>0.00102145045965</bin>
      </cell>
      <cell lat='38.8' lon='141.6'>
        <bin m='3.0'>0.00102145045965</bin>
      </cell>
      <cell lat='38.9' lon='141.6'>
        <bin m='3.0'>0.00102145045965</bin>
      </cell>
      <cell lat='39.0' lon='141.6'>
        <bin m='3.0'>0.00102145045965</bin>
      </cell>
      <cell lat='39.1' lon='141.6'>
        <bin m='3.0'>0.00102145045965</bin>
      </cell>
      <cell lat='39.2' lon='141.6'>
        <bin m='3.0'>0.00102145045965</bin>
      </cell>
      <cell lat='39.3' lon='141.6'>
        <bin m='3.0'>0.00102145045965</bin>
      </cell>
      <cell lat='39.4' lon='141.6'>
        <bin m='3.0'>0.00102145045965</bin>
      </cell>
      <cell lat='39.5' lon='141.6'>
        <bin m='3.0'>0.00102145045965</bin>
      </cell>
      <cell lat='39.6' lon='141.6'>
        <bin m='3.0'>0.00102145045965</bin>
      </cell>
      <cell lat='39.7' lon='141.6'>
        <bin m='3.0'>0.00102145045965</bin>
      </cell>
      <cell lat='39.8' lon='141.6'>
        <bin m='3.0'>0.00102145045965</bin>
      </cell>
      <cell lat='39.9' lon='141.6'>
        <bin m='3.0'>0.00102145045965</bin>
      </cell>
      <cell lat='40.0' lon='141.6'>
        <bin m='3.0'>0.00102145045965</bin>
      </cell>
      <cell lat='40.1' lon='141.6'>
        <bin m='3.0'>0.00102145045965</bin>
      </cell>
      <cell lat='40.2' lon='141.6'>
        <bin m='3.0'>0.00102145045965</bin>
      </cell>
      <cell lat='40.3' lon='141.6'>
        <bin m='3.0'>0.00102145045965</bin>
      </cell>
      <cell lat='40.4' lon='141.6'>
        <bin m='3.0'>0.00102145045965</bin>
      </cell>
      <cell lat='40.5' lon='141.6'>
        <bin m='3.0'>0.00102145045965</bin>
      </cell>
      <cell lat='40.6' lon='141.6'>
        <bin m='3.0'>0.00102145045965</bin>
      </cell>
      <cell lat='40.7' lon='141.6'>
        <bin m='3.0'>0.00102145045965</bin>
      </cell>
      <cell lat='40.8' lon='141.6'>
        <bin m='3.0'>0.00102145045965</bin>
      </cell>
      <cell lat='40.9' lon='141.6'>
        <bin m='3.0'>0.00102145045965</bin>
      </cell>
      <cell lat='37.0' lon='141.7'>
        <bin m='3.0'>0.00102145045965</bin>
      </cell>
      <cell lat='37.1' lon='141.7'>
        <bin m='3.0'>0.00102145045965</bin>
      </cell>
      <cell lat='37.2' lon='141.7'>
        <bin m='3.0'>0.00102145045965</bin>
      </cell>
      <cell lat='37.3' lon='141.7'>
        <bin m='3.0'>0.00102145045965</bin>
      </cell>
      <cell lat='37.4' lon='141.7'>
        <bin m='3.0'>0.00102145045965</bin>
      </cell>
      <cell lat='37.5' lon='141.7'>
        <bin m='3.0'>0.00102145045965</bin>
      </cell>
      <cell lat='37.6' lon='141.7'>
        <bin m='3.0'>0.00102145045965</bin>
      </cell>
      <cell lat='37.7' lon='141.7'>
        <bin m='3.0'>0.00102145045965</bin>
      </cell>
      <cell lat='37.8' lon='141.7'>
        <bin m='3.0'>0.00102145045965</bin>
      </cell>
      <cell lat='37.9' lon='141.7'>
        <bin m='3.0'>0.00102145045965</bin>
      </cell>
      <cell lat='38.0' lon='141.7'>
        <bin m='3.0'>0.00102145045965</bin>
      </cell>
      <cell lat='38.1' lon='141.7'>
        <bin m='3.0'>0.00102145045965</bin>
      </cell>
      <cell lat='38.2' lon='141.7'>
        <bin m='3.0'>0.00102145045965</bin>
      </cell>
      <cell lat='38.3' lon='141.7'>
        <bin m='3.0'>0.00102145045965</bin>
      </cell>
      <cell lat='38.4' lon='141.7'>
        <bin m='3.0'>0.00102145045965</bin>
      </cell>
      <cell lat='38.5' lon='141.7'>
        <bin m='3.0'>0.00102145045965</bin>
      </cell>
      <cell lat='38.6' lon='141.7'>
        <bin m='3.0'>0.00102145045965</bin>
      </cell>
      <cell lat='38.7' lon='141.7'>
        <bin m='3.0'>0.00102145045965</bin>
      </cell>
      <cell lat='38.8' lon='141.7'>
        <bin m='3.0'>0.00102145045965</bin>
      </cell>
      <cell lat='38.9' lon='141.7'>
        <bin m='3.0'>0.00102145045965</bin>
      </cell>
      <cell lat='39.0' lon='141.7'>
        <bin m='3.0'>0.00102145045965</bin>
      </cell>
      <cell lat='39.1' lon='141.7'>
        <bin m='3.0'>0.00102145045965</bin>
      </cell>
      <cell lat='39.2' lon='141.7'>
        <bin m='3.0'>0.00102145045965</bin>
      </cell>
      <cell lat='39.3' lon='141.7'>
        <bin m='3.0'>0.00102145045965</bin>
      </cell>
      <cell lat='39.4' lon='141.7'>
        <bin m='3.0'>0.00102145045965</bin>
      </cell>
      <cell lat='39.5' lon='141.7'>
        <bin m='3.0'>0.00102145045965</bin>
      </cell>
      <cell lat='39.6' lon='141.7'>
        <bin m='3.0'>0.00102145045965</bin>
      </cell>
      <cell lat='39.7' lon='141.7'>
        <bin m='3.0'>0.00102145045965</bin>
      </cell>
      <cell lat='39.8' lon='141.7'>
        <bin m='3.0'>0.00102145045965</bin>
      </cell>
      <cell lat='39.9' lon='141.7'>
        <bin m='3.0'>0.00102145045965</bin>
      </cell>
      <cell lat='40.0' lon='141.7'>
        <bin m='3.0'>0.00102145045965</bin>
      </cell>
      <cell lat='40.1' lon='141.7'>
        <bin m='3.0'>0.00102145045965</bin>
      </cell>
      <cell lat='40.2' lon='141.7'>
        <bin m='3.0'>0.00102145045965</bin>
      </cell>
      <cell lat='40.3' lon='141.7'>
        <bin m='3.0'>0.00102145045965</bin>
      </cell>
      <cell lat='40.4' lon='141.7'>
        <bin m='3.0'>0.00102145045965</bin>
      </cell>
      <cell lat='40.5' lon='141.7'>
        <bin m='3.0'>0.00102145045965</bin>
      </cell>
      <cell lat='40.6' lon='141.7'>
        <bin m='3.0'>0.00102145045965</bin>
      </cell>
      <cell lat='40.7' lon='141.7'>
        <bin m='3.0'>0.00102145045965</bin>
      </cell>
      <cell lat='40.8' lon='141.7'>
        <bin m='3.0'>0.00102145045965</bin>
      </cell>
      <cell lat='40.9' lon='141.7'>
        <bin m='3.0'>0.00102145045965</bin>
      </cell>
    </depthLayer>
  </forecastData>
</CSEPForecast>
